<?xml version="1.0" encoding="utf-8"?>
<odoo>
    <data noupdate="1">        

        <!-- 重置密码的消息模板-->
        <record id="auth_signup.reset_password_email" model="mail.template">
            <field name="wxwork_body_html" type="html">
# Your Account

Dear ${object.name},  
  
A password reset was requested for the Odoo account linked to this email.
You may change your password by following this link which will remain valid during 24 hours:

[Change password](${object.signup_url})

If you do not expect this, you can safely ignore this email.  
  
Thanks,
% if user.signature:  
    ${user.signature | safe} 
% endif  
#
**${object.company_id.name}**
 
${object.company_id.phone} 
    % if object.company_id.email 
    |[${object.company_id.email}]('mailto:%s' % ${object.company_id.email}) 
% endif
% if object.company_id.website 
    | [${object.company_id.website}]('%s' %${object.company_id.website}) 
% endif             
            </field>
        </record>

        <!-- 新用户的消息模板-->
        <record id="auth_signup.set_password_email" model="mail.template">
            <field name="wxwork_body_html" type="html">
Welcome to Odoo
# ${object.name}

Dear ${object.name},  
  
You have been invited by ${object.create_uid.name} of ${object.company_id.name} to connect on Odoo.

[Accept invitation](${object.signup_url})

% set website_url = object.env['ir.config_parameter'].sudo().get_param('web.base.url') Your Odoo domain is: **[${website_url}](${website_url})**

Your sign in email is: <a target='_blank' href='/web/login?login=${object.email}'>${object.email}</a>

Never heard of Odoo? It’s an all-in-one business software loved by 3+ million users. It will considerably improve your experience at work and increase your productivity.

Have a look at the <font color='warning'><a href='https://www.odoo.com/page/tour?utm_source=db&amp;utm_medium=auth' target='_blank'>Odoo Tour</a></font> to discover the tool.

Enjoy Odoo!

The ${object.company_id.name} Team

#  
**${object.company_id.name}**
 
${object.company_id.phone} 
    % if object.company_id.email 
    |[${object.company_id.email}]('mailto:%s' % ${object.company_id.email}) 
% endif
% if object.company_id.website 
    | [${object.company_id.website}]('%s' %${object.company_id.website}) 
% endif            
            </field>
        </record>
        

        <!-- 使用注册令牌的新用户的消息模板-->
        <record id="auth_signup.mail_template_user_signup_account_created" model="mail.template">
            <field name="wxwork_body_html" type="html">
Your Account
# ${object.name}

Dear ${object.name},  
  
Your account has been successfully created!

Your login is **${object.email}**

To gain access to your account, you can use the following link:

<font color='warning'>[Go to My Account](/web/login?auth_login=${object.email})</font>

Thanks,

% if user.signature:
    ${user.signature | safe}
% endif
  

#  
**${object.company_id.name}**
 
${object.company_id.phone} 
    % if object.company_id.email 
    |[${object.company_id.email}]('mailto:%s' % ${object.company_id.email}) 
% endif
% if object.company_id.website 
    | [${object.company_id.website}]('%s' %${object.company_id.website}) 
% endif           
            </field>
        </record>


        <!-- 用于提醒未注册用户的消息模板-->
        <record id="auth_signup.mail_template_data_unregistered_users" model="mail.template">
            <field name="wxwork_body_html" type="html">
% set invited_users = ctx['invited_users']
# Pending Invitations

Dear ${object.name or ''}, 
  
You added the following user(s) to your database but they haven't registered yet:

% for invited_user in invited_users:
####   ${invited_user}
% endfor
  
Follow up with them so they can access your database and start working with you.

Have a nice day!

The ${object.company_id.name} Team
#          
            </field>
        </record>


    </data>
</odoo>